sudo_win32_extras/__init__.py
sudo_win32_extras/cli.py
sudo_win32_extras-1.0.0.dist-info/LICENSE
sudo_win32_extras-1.0.0.dist-info/METADATA
sudo_win32_extras-1.0.0.dist-info/WHEEL
sudo_win32_extras-1.0.0.dist-info/entry_points.txt
sudo_win32_extras-1.0.0.dist-info/top_level.txt
sudo_win32_extras-1.0.0.dist-info/RECORD
