Metadata-Version: 2.1
Name: sudo_win32_extras
Version: 1.0.0
Summary: Contains the sudo command for the sudo_win32[sudo]
Home-page: https://github.com/zackees/sudo-win32-extras
Maintainer: Zachary Vorhies
License: BSD 3-Clause License
Keywords: template-python-cmd
Classifier: Programming Language :: Python :: 3
Requires-Python: >=3.7
License-File: LICENSE
